{
  "swagger": "2.0",
  "info": {
    "description": "Api Documentation",
    "version": "1.0",
    "title": "Api Documentation",
    "termsOfService": "urn:tos",
    "contact": {},
    "license": {
      "name": "Apache 2.0",
      "url": "http://www.apache.org/licenses/LICENSE-2.0"
    }
  },
  "host": "18.139.50.74:8080",
  "securityDefinitions": {
    "Bearer": {
      "type": "apiKey",
      "in": "header",
      "name": "Authorization"
    }
  },
  "basePath": "/",
  "tags": [
    {
      "name": "auth-controller",
      "description": "Auth Controller"
    },
    {
      "name": "checklist-controller",
      "description": "Checklist Controller"
    },
    {
      "name": "checklist-item-controller",
      "description": "Checklist Item Controller"
    }
  ],
  "paths": {
    "/checklist": {
      "get": {
        "security": [
          {
            "Bearer": []
          }
        ],
        "tags": [
          "checklist-controller"
        ],
        "summary": "getAll",
        "operationId": "getAllUsingGET",
        "produces": [
          "*/*"
        ],
        "responses": {
          "200": {
            "description": "OK",
            "schema": {
              "type": "object"
            }
          },
          "401": {
            "description": "Unauthorized"
          },
          "403": {
            "description": "Forbidden"
          },
          "404": {
            "description": "Not Found"
          }
        },
        "deprecated": false
      },
      "post": {
        "security": [
          {
            "Bearer": []
          }
        ],
        "tags": [
          "checklist-controller"
        ],
        "summary": "save",
        "operationId": "saveUsingPOST",
        "consumes": [
          "application/json"
        ],
        "produces": [
          "*/*"
        ],
        "parameters": [
          {
            "in": "body",
            "name": "checklistRequestDto",
            "description": "checklistRequestDto",
            "required": true,
            "schema": {
              "$ref": "#/definitions/ChecklistRequestDto"
            }
          }
        ],
        "responses": {
          "200": {
            "description": "OK",
            "schema": {
              "type": "object"
            }
          },
          "201": {
            "description": "Created"
          },
          "401": {
            "description": "Unauthorized"
          },
          "403": {
            "description": "Forbidden"
          },
          "404": {
            "description": "Not Found"
          }
        },
        "deprecated": false
      }
    },
    "/checklist/{checklistId}": {
      "delete": {
        "security": [
          {
            "Bearer": []
          }
        ],
        "tags": [
          "checklist-controller"
        ],
        "summary": "deleteById",
        "operationId": "deleteByIdUsingDELETE",
        "produces": [
          "*/*"
        ],
        "parameters": [
          {
            "name": "checklistId",
            "in": "path",
            "description": "checklistId",
            "required": true,
            "type": "integer",
            "format": "int64"
          }
        ],
        "responses": {
          "200": {
            "description": "OK",
            "schema": {
              "type": "object"
            }
          },
          "204": {
            "description": "No Content"
          },
          "401": {
            "description": "Unauthorized"
          },
          "403": {
            "description": "Forbidden"
          }
        },
        "deprecated": false
      }
    },
    "/item": {
      "post": {
        "security": [
          {
            "Bearer": []
          }
        ],
        "tags": [
          "checklist-item-controller"
        ],
        "summary": "save",
        "operationId": "saveUsingPOST_1",
        "consumes": [
          "application/json"
        ],
        "produces": [
          "*/*"
        ],
        "parameters": [
          {
            "in": "body",
            "name": "requestDto",
            "description": "requestDto",
            "required": true,
            "schema": {
              "$ref": "#/definitions/ChecklistItemRequestDto"
            }
          }
        ],
        "responses": {
          "200": {
            "description": "OK",
            "schema": {
              "type": "object"
            }
          },
          "201": {
            "description": "Created"
          },
          "401": {
            "description": "Unauthorized"
          },
          "403": {
            "description": "Forbidden"
          },
          "404": {
            "description": "Not Found"
          }
        },
        "deprecated": false
      }
    },
    "/item/rename/{id}": {
      "put": {
        "security": [
          {
            "Bearer": []
          }
        ],
        "tags": [
          "checklist-item-controller"
        ],
        "summary": "renameItem",
        "operationId": "renameItemUsingPUT",
        "consumes": [
          "application/json"
        ],
        "produces": [
          "*/*"
        ],
        "parameters": [
          {
            "name": "id",
            "in": "path",
            "description": "id",
            "required": true,
            "type": "integer",
            "format": "int64"
          },
          {
            "in": "body",
            "name": "requestDto",
            "description": "requestDto",
            "required": true,
            "schema": {
              "$ref": "#/definitions/ChecklistItemRequestDto"
            }
          }
        ],
        "responses": {
          "200": {
            "description": "OK",
            "schema": {
              "type": "object"
            }
          },
          "201": {
            "description": "Created"
          },
          "401": {
            "description": "Unauthorized"
          },
          "403": {
            "description": "Forbidden"
          },
          "404": {
            "description": "Not Found"
          }
        },
        "deprecated": false
      }
    },
    "/item/{id}": {
      "get": {
        "security": [
          {
            "Bearer": []
          }
        ],
        "tags": [
          "checklist-item-controller"
        ],
        "summary": "getById",
        "operationId": "getByIdUsingGET",
        "produces": [
          "*/*"
        ],
        "parameters": [
          {
            "name": "id",
            "in": "path",
            "description": "id",
            "required": true,
            "type": "integer",
            "format": "int64"
          }
        ],
        "responses": {
          "200": {
            "description": "OK",
            "schema": {
              "type": "object"
            }
          },
          "401": {
            "description": "Unauthorized"
          },
          "403": {
            "description": "Forbidden"
          },
          "404": {
            "description": "Not Found"
          }
        },
        "deprecated": false
      },
      "put": {
        "security": [
          {
            "Bearer": []
          }
        ],
        "tags": [
          "checklist-item-controller"
        ],
        "summary": "updateItemStatus",
        "operationId": "updateItemStatusUsingPUT",
        "consumes": [
          "application/json"
        ],
        "produces": [
          "*/*"
        ],
        "parameters": [
          {
            "name": "id",
            "in": "path",
            "description": "id",
            "required": true,
            "type": "integer",
            "format": "int64"
          }
        ],
        "responses": {
          "200": {
            "description": "OK",
            "schema": {
              "type": "object"
            }
          },
          "201": {
            "description": "Created"
          },
          "401": {
            "description": "Unauthorized"
          },
          "403": {
            "description": "Forbidden"
          },
          "404": {
            "description": "Not Found"
          }
        },
        "deprecated": false
      },
      "delete": {
        "security": [
          {
            "Bearer": []
          }
        ],
        "tags": [
          "checklist-item-controller"
        ],
        "summary": "deleteItem",
        "operationId": "deleteItemUsingDELETE",
        "produces": [
          "*/*"
        ],
        "parameters": [
          {
            "name": "id",
            "in": "path",
            "description": "id",
            "required": true,
            "type": "integer",
            "format": "int64"
          }
        ],
        "responses": {
          "200": {
            "description": "OK",
            "schema": {
              "type": "object"
            }
          },
          "204": {
            "description": "No Content"
          },
          "401": {
            "description": "Unauthorized"
          },
          "403": {
            "description": "Forbidden"
          }
        },
        "deprecated": false
      }
    },
    "/login": {
      "post": {
        "tags": [
          "auth-controller"
        ],
        "summary": "login",
        "operationId": "loginUsingPOST",
        "consumes": [
          "application/json"
        ],
        "produces": [
          "*/*"
        ],
        "parameters": [
          {
            "in": "body",
            "name": "loginDto",
            "description": "loginDto",
            "required": true,
            "schema": {
              "$ref": "#/definitions/LoginRequestDto"
            }
          }
        ],
        "responses": {
          "200": {
            "description": "OK",
            "schema": {
              "type": "object"
            }
          },
          "201": {
            "description": "Created"
          },
          "401": {
            "description": "Unauthorized"
          },
          "403": {
            "description": "Forbidden"
          },
          "404": {
            "description": "Not Found"
          }
        },
        "deprecated": false
      }
    },
    "/register": {
      "post": {
        "tags": [
          "auth-controller"
        ],
        "summary": "register",
        "operationId": "registerUsingPOST",
        "consumes": [
          "application/json"
        ],
        "produces": [
          "*/*"
        ],
        "parameters": [
          {
            "in": "body",
            "name": "requestDto",
            "description": "requestDto",
            "required": true,
            "schema": {
              "$ref": "#/definitions/UserAccountRequestDto"
            }
          }
        ],
        "responses": {
          "200": {
            "description": "OK",
            "schema": {
              "type": "object"
            }
          },
          "201": {
            "description": "Created"
          },
          "401": {
            "description": "Unauthorized"
          },
          "403": {
            "description": "Forbidden"
          },
          "404": {
            "description": "Not Found"
          }
        },
        "deprecated": false
      }
    }
  },
  "definitions": {
    "ChecklistItemRequestDto": {
      "type": "object",
      "properties": {
        "checklistId": {
          "type": "integer",
          "format": "int64"
        },
        "itemName": {
          "type": "string"
        }
      },
      "title": "ChecklistItemRequestDto"
    },
    "ChecklistRequestDto": {
      "type": "object",
      "properties": {
        "name": {
          "type": "string"
        }
      },
      "title": "ChecklistRequestDto"
    },
    "LoginRequestDto": {
      "type": "object",
      "properties": {
        "password": {
          "type": "string"
        },
        "username": {
          "type": "string"
        }
      },
      "title": "LoginRequestDto"
    },
    "UserAccountRequestDto": {
      "type": "object",
      "properties": {
        "email": {
          "type": "string"
        },
        "password": {
          "type": "string"
        },
        "username": {
          "type": "string"
        }
      },
      "title": "UserAccountRequestDto"
    }
  }
}